.gitignore
CHANGES.txt
README.md
setup.py
djinn_workflow/__init__.py
djinn_workflow/signals.py
djinn_workflow/utils.py
djinn_workflow.egg-info/PKG-INFO
djinn_workflow.egg-info/SOURCES.txt
djinn_workflow.egg-info/dependency_links.txt
djinn_workflow.egg-info/entry_points.txt
djinn_workflow.egg-info/not-zip-safe
djinn_workflow.egg-info/requires.txt
djinn_workflow.egg-info/top_level.txt
djinn_workflow/models/__init__.py
djinn_workflow/models/modelworkflow.py
djinn_workflow/models/objectstate.py
djinn_workflow/models/permissionassignment.py
djinn_workflow/models/signal_processors.py
djinn_workflow/models/state.py
djinn_workflow/models/transition.py
djinn_workflow/models/workflow.py
djinn_workflow/templatetags/__init__.py
djinn_workflow/templatetags/djinn_workflow_tags.py
djinn_workflow/tests/__init__.py
djinn_workflow/tests/test_utils.py
djinn_workflow/tests/test_workflow.py