Metadata-Version: 1.1
Name: djinn-workflow
Version: 1.0.0
Summary: Djinn Intranet workflow module
Home-page: https://github.com/PythonUnited/djinn_workflow
Author: PythonUnited
Author-email: info@pythonunited.com
License: beer-ware
Keywords: Djinn workflow
Platform: UNKNOWN
Classifier: Development Status :: 3 - Alpha
Classifier: Framework :: Django
Classifier: Intended Audience :: Developers
Classifier: License :: Freely Distributable
Classifier: Programming Language :: Python
Classifier: Topic :: Internet :: WWW/HTTP :: Site Management
Classifier: Topic :: Software Development :: Libraries :: Application Frameworks
